icron/__init__.py
icron/schedule.py
icron-0.0.1.dist-info/LICENSE
icron-0.0.1.dist-info/METADATA
icron-0.0.1.dist-info/WHEEL
icron-0.0.1.dist-info/top_level.txt
icron-0.0.1.dist-info/RECORD
